<annotation>
	<folder>video_2</folder>
	<filename>video_2-planta-025-patche-023.jpg</filename>
	<path>C:\Users\gabri\OneDrive\Área de Trabalho\tcc_1\1_imagens\video_2\video_2-planta-025-patche-023.jpg</path>
	<source>
		<database>Unknown</database>
	</source>
	<size>
		<width>512</width>
		<height>512</height>
		<depth>3</depth>
	</size>
	<segmented>0</segmented>
	<object>
		<name>acerola</name>
		<pose>Unspecified</pose>
		<truncated>0</truncated>
		<difficult>0</difficult>
		<bndbox>
			<xmin>321</xmin>
			<ymin>142</ymin>
			<xmax>358</xmax>
			<ymax>189</ymax>
		</bndbox>
	</object>
	<object>
		<name>acerola</name>
		<pose>Unspecified</pose>
		<truncated>0</truncated>
		<difficult>0</difficult>
		<bndbox>
			<xmin>286</xmin>
			<ymin>297</ymin>
			<xmax>321</xmax>
			<ymax>336</ymax>
		</bndbox>
	</object>
	<object>
		<name>acerola</name>
		<pose>Unspecified</pose>
		<truncated>0</truncated>
		<difficult>0</difficult>
		<bndbox>
			<xmin>374</xmin>
			<ymin>2</ymin>
			<xmax>416</xmax>
			<ymax>37</ymax>
		</bndbox>
	</object>
</annotation>
